commandeer/__init__.py
commandeer-0.3.1.dist-info/LICENSE
commandeer-0.3.1.dist-info/WHEEL
commandeer-0.3.1.dist-info/METADATA
commandeer-0.3.1.dist-info/RECORD
