Metadata-Version: 2.1
Name: commandeer
Version: 0.3.1
Summary: A command-line parser library
Home-page: https://gitlab.com/jspielmann/commandeer
License: GPL-3.0-or-later
Author: Johannes Spielmann
Author-email: j@spielmannsolutions.com
Requires-Python: >=3.6,<4.0
Classifier: Development Status :: 5 - Production/Stable
Classifier: Environment :: Console
Classifier: Intended Audience :: Developers
Classifier: License :: OSI Approved :: GNU General Public License v3 or later (GPLv3+)
Classifier: Operating System :: OS Independent
Classifier: Programming Language :: Python :: 3
Classifier: Programming Language :: Python :: 3.6
Classifier: Programming Language :: Python :: 3.7
Classifier: Programming Language :: Python :: 3.8
Classifier: Programming Language :: Python :: 3.9
Classifier: Programming Language :: Python :: 3.10
Project-URL: Documentation, https://commandeer.readthedocs.io/en/latest/
Project-URL: Repository, https://gitlab.com/jspielmann/commandeer
